csm/__init__.py
csm/client.py
csm/version.py
csm_ai-0.1.9.dist-info/licenses/LICENSE
csm_ai-0.1.9.dist-info/METADATA
csm_ai-0.1.9.dist-info/WHEEL
csm_ai-0.1.9.dist-info/top_level.txt
csm_ai-0.1.9.dist-info/RECORD
