Metadata-Version: 2.4
Name: csm-ai
Version: 0.1.9
Summary: The official Python library for the CSM API
Home-page: https://github.com/CommonSenseMachines/csm-ai
Author: Common Sense Machines
Author-email: support@csm.ai
Classifier: Programming Language :: Python :: 3
Classifier: License :: OSI Approved :: Apache Software License
License-File: LICENSE
Requires-Dist: requests
Requires-Dist: pillow
Dynamic: author
Dynamic: author-email
Dynamic: classifier
Dynamic: description
Dynamic: description-content-type
Dynamic: home-page
Dynamic: license-file
Dynamic: requires-dist
Dynamic: summary
